ReactiveMode/__init__.py
ReactiveMode/main.py
ReactiveMode-0.1.dist-info/METADATA
ReactiveMode-0.1.dist-info/WHEEL
ReactiveMode-0.1.dist-info/top_level.txt
ReactiveMode-0.1.dist-info/RECORD
