Metadata-Version: 2.1
Name: ReactiveMode
Version: 0.1
Summary: Small Python Library About Events.
Home-page: UNKNOWN
Author: FallingXbot
License: UNKNOWN
Platform: UNKNOWN
